bratly/io/__init__.py
bratly/io/ann_write_src.py
bratly/io/file_read_src.py
bratly/io/py.typed
bratly_io_fs-0.1.4.dist-info/WHEEL
bratly_io_fs-0.1.4.dist-info/METADATA
bratly_io_fs-0.1.4.dist-info/RECORD
